pyopenapi_gen/__init__.py
pyopenapi_gen/__main__.py
pyopenapi_gen/cli.py
pyopenapi_gen/http_types.py
pyopenapi_gen/ir.py
pyopenapi_gen/py.typed
pyopenapi_gen/context/CLAUDE.md
pyopenapi_gen/context/file_manager.py
pyopenapi_gen/context/import_collector.py
pyopenapi_gen/context/render_context.py
pyopenapi_gen/core/CLAUDE.md
pyopenapi_gen/core/__init__.py
pyopenapi_gen/core/cattrs_converter.py
pyopenapi_gen/core/exceptions.py
pyopenapi_gen/core/http_status_codes.py
pyopenapi_gen/core/http_transport.py
pyopenapi_gen/core/pagination.py
pyopenapi_gen/core/postprocess_manager.py
pyopenapi_gen/core/spec_fetcher.py
pyopenapi_gen/core/streaming_helpers.py
pyopenapi_gen/core/telemetry.py
pyopenapi_gen/core/utils.py
pyopenapi_gen/core/warning_collector.py
pyopenapi_gen/core/auth/base.py
pyopenapi_gen/core/auth/plugins.py
pyopenapi_gen/core/loader/__init__.py
pyopenapi_gen/core/loader/loader.py
pyopenapi_gen/core/loader/operations/__init__.py
pyopenapi_gen/core/loader/operations/parser.py
pyopenapi_gen/core/loader/operations/post_processor.py
pyopenapi_gen/core/loader/operations/request_body.py
pyopenapi_gen/core/loader/parameters/__init__.py
pyopenapi_gen/core/loader/parameters/parser.py
pyopenapi_gen/core/loader/responses/__init__.py
pyopenapi_gen/core/loader/responses/parser.py
pyopenapi_gen/core/loader/schemas/__init__.py
pyopenapi_gen/core/loader/schemas/extractor.py
pyopenapi_gen/core/parsing/__init__.py
pyopenapi_gen/core/parsing/context.py
pyopenapi_gen/core/parsing/cycle_helpers.py
pyopenapi_gen/core/parsing/schema_finalizer.py
pyopenapi_gen/core/parsing/schema_parser.py
pyopenapi_gen/core/parsing/unified_cycle_detection.py
pyopenapi_gen/core/parsing/common/__init__.py
pyopenapi_gen/core/parsing/common/type_parser.py
pyopenapi_gen/core/parsing/common/ref_resolution/__init__.py
pyopenapi_gen/core/parsing/common/ref_resolution/resolve_schema_ref.py
pyopenapi_gen/core/parsing/common/ref_resolution/helpers/__init__.py
pyopenapi_gen-2.7.2.dist-info/METADATA
pyopenapi_gen-2.7.2.dist-info/WHEEL
pyopenapi_gen-2.7.2.dist-info/entry_points.txt
pyopenapi_gen-2.7.2.dist-info/licenses/LICENSE
pyopenapi_gen-2.7.2.dist-info/RECORD
