Metadata-Version: 2.4
Name: pyopenapi-gen
Version: 2.7.2
Summary: Modern, async-first Python client generator for OpenAPI specifications with advanced cycle detection and unified type resolution
Project-URL: Homepage, https://github.com/your-org/pyopenapi-gen
Project-URL: Documentation, https://github.com/your-org/pyopenapi-gen/blob/main/README.md
Project-URL: Repository, https://github.com/your-org/pyopenapi-gen
Project-URL: Issues, https://github.com/your-org/pyopenapi-gen/issues
Project-URL: Changelog, https://github.com/your-org/pyopenapi-gen/blob/main/CHANGELOG.md
Project-URL: Bug Reports, https://github.com/your-org/pyopenapi-gen/issues
Project-URL: Source Code, https://github.com/your-org/pyopenapi-gen
Author-email: Mindhive Oy <contact@mindhive.fi>
Maintainer-email: Ville Venäläinen | Mindhive Oy <ville@mindhive.fi>
License: MIT
License-File: LICENSE
Keywords: api,async,client,code-generation,enterprise,generator,http,openapi,python,rest,swagger,type-safe
Classifier: Development Status :: 4 - Beta
Classifier: Environment :: Console
Classifier: Framework :: AsyncIO
Classifier: Intended Audience :: Developers
Classifier: License :: OSI Approved :: MIT License
Classifier: Natural Language :: English
Classifier: Operating System :: MacOS
Classifier: Operating System :: Microsoft :: Windows
Classifier: Operating System :: POSIX :: Linux
Classifier: Programming Language :: Python :: 3
Classifier: Programming Language :: Python :: 3 :: Only
Classifier: Programming Language :: Python :: 3.12
Classifier: Topic :: Internet :: WWW/HTTP :: HTTP Servers
Classifier: Topic :: Software Development :: Code Generators
Classifier: Topic :: Software Development :: Libraries :: Python Modules
Classifier: Topic :: System :: Networking
Classifier: Typing :: Typed
Requires-Python: <4.0.0,>=3.12
Requires-Dist: cattrs>=25.3.0
Requires-Dist: click>=8.0.0
Requires-Dist: dataclass-wizard<0.37.0,>=0.36.1
Requires-Dist: httpx>=0.24.0
Requires-Dist: openapi-core>=0.19
Requires-Dist: openapi-spec-validator>=0.7
Requires-Dist: pyyaml>=6.0
Requires-Dist: typer>=0.14.0
Requires-Dist: urllib3<3.0.0,>=2.6.0
Provides-Extra: dev
Requires-Dist: bandit[toml]>=1.7.0; extra == 'dev'
Requires-Dist: black>=23.0; extra == 'dev'
Requires-Dist: dataclass-wizard>=0.22.0; extra == 'dev'
Requires-Dist: httpx>=0.24.0; extra == 'dev'
Requires-Dist: mypy>=1.7; extra == 'dev'
Requires-Dist: pytest-asyncio>=0.20.0; extra == 'dev'
Requires-Dist: pytest-cov>=4.0; extra == 'dev'
Requires-Dist: pytest-timeout>=2.1.0; extra == 'dev'
Requires-Dist: pytest-xdist>=3.0.0; extra == 'dev'
Requires-Dist: pytest>=7.0; extra == 'dev'
Requires-Dist: ruff>=0.4; extra == 'dev'
Requires-Dist: safety>=2.0.0; extra == 'dev'
Requires-Dist: types-pyyaml>=6.0.12; extra == 'dev'
Requires-Dist: types-toml>=0.10.8; extra == 'dev'
